bli/bli.py
bli-0.1.2b0.dist-info/entry_points.txt
bli-0.1.2b0.dist-info/WHEEL
bli-0.1.2b0.dist-info/METADATA
bli-0.1.2b0.dist-info/RECORD
