Metadata-Version: 2.1
Name: bli
Version: 0.1.2b0
Summary: A todo-list manager with bullet-journal mechanisms
Home-page: https://github.com/Erawpalassalg/clj
License: MIT
Author: erawpalassalg
Author-email: mael.arnaud@gmail.com
Classifier: Development Status :: 4 - Beta
Classifier: Environment :: Console
Classifier: License :: OSI Approved :: MIT License
Classifier: Programming Language :: Python :: 2
Classifier: Programming Language :: Python :: 2.7
Classifier: Programming Language :: Python :: 3
Classifier: Programming Language :: Python :: 3.4
Classifier: Programming Language :: Python :: 3.5
Classifier: Programming Language :: Python :: 3.6
Classifier: Programming Language :: Python :: 3.7
Classifier: Programming Language :: Python :: 3.8
Classifier: Topic :: Office/Business :: News/Diary
